[
    {
        "DATE": "2024-07-15T20:56:06.341-05:00",
        "SO_LINE": 1,
        "PO_NO": 290290302,
        "CUSTOMER_ID": 1000,
        "ORDER_TAKEN_BY": "EDI",
        "ORDER_PROCESSED_BY": "EDI",
        "ORDER_TYPE": "R",
        "ITEM": "GRILLE_ASERIES",
        "CUSTOMER_PART_NUMBER": "0348729001122024GRL04",
        "QUANTITY": 1,
        "UNITS": "EA",
        "LOCATION": "230 MOUNDS VIEW",
        "EXPECTED_SHIP_DATE": "15/07/2024",
        "CONFIGURATOR_ID": "CPQ_00001",
        "internalID": "<INTERNAL_ID>",
        "IGNOREME1": "CUSTOM FIELDS STARTS NEXT COLUMN",
        "Batch_Bin_Handing": "DVS099534/001/0001U",
        "Cart_No": "CARTNO",
        "Color": "WH",
        "Description": "2860 WH ADL EXTERIOR APPLIED GRILLE  ADH EXTRUPR",
        "Dock": "DOCK",
        "Finish": "PAINTED",
        "Pattern": "SEL",
        "HIDX": 12.728,
        "H_LI": 15.527,
        "Handing": "0001U",
        "Height": 31.062,
        "HorizontalAlign": "ADH",
        "HorizontalProfile": 0.875,
        "PanesTall": 2,
        "PanesWide": 2,
        "Material": "FBX",
        "OrderType": "AW850",
        "PackType": "R",
        "ProductLine": "ADH",
        "ReferenceID": "0348729001122024GRL04",
        "ProductSeries": 400,
        "Slot_No": "SLOTNO",
        "Unit_Height": 71.25,
        "Unit_Width": 31.25,
        "VIDX": 15.834,
        "VerticalProfile": 0.875,
        "V_LI": 12.416,
        "Warehouse": "A1GN01",
        "Draw#": "NULL",
        "EJLen": 0,
        "EJDepth": 31.062,
        "Location": 98388,
        "Type": "EXTRUPR",
        "TAPEFLAG": "FDL",
        "Batch": 99,
        "Bin": 1,
        "ExteriorColor": "PR",
        "InteriorColor": "WH",
        "HIDXCTR": "NULL",
        "VIDXCTR": "NULL",
        "UnitSize": 2860,
        "FixedHorizontalQty": "NULL",
        "FixedVerticalQty": "NULL",
        "FixedCheckRailQty": "NULL",
        "FixedHorizontalLength": "NULL",
        "FixedVerticalLength": "NULL",
        "Fixed Unit": "NULL",
        "Price": 17.68,
        "LoadId": "LOADID",
        "JobPrefix": "Job Prefix",
        "VendorNum": "VENDORNUM",
        "PO_LINE": 1,
        "IGNOREME2": "CUSTOM FIELDS ENDED LAST COLUMN",
        "FILE_ID": "<FILE_ID>",
        "ATTRIBUTES": {
            "PO_NO": 290290302,
            "SO_LINE": 1,
            "CUSTOMER_ID": 1000,
            "ORDERTYPE/ORDERTYPE": "AW850",
            "UNITSIZE/UNITSIZE": 2860,
            "PATTERN/PATTERN": "SEL",
            "PRODUCTLINE/PRODUCTLINE": "ADH",
            "FIXEDUNITINFO/FIXEDUNIT": "NULL",
            "FIXEDUNITINFO/FIXEDHORIZQTY": "NULL",
            "FIXEDUNITINFO/FIXEDVERTQTY": "NULL",
            "FIXEDUNITINFO/FIXEDCHKRAILQTY": "NULL",
            "FIXEDUNITINFO/FIXEDHORIZLENGTH": "NULL",
            "FIXEDUNITINFO/FIXEDVERTLENGTH": "NULL",
            "TYPE/TYPE": "EXTRUPR",
            "SPECIES/SPECIES": "FBX",
            "TAPEFLAG/TAPEFLAG": "FDL",
            "FINISH/FINISH": "PAINTED",
            "COLOR/INT_COLOR": "WH",
            "COLOR/EXT_COLOR": "PR",
            "VERT_INFO/VERTICALLENGTH": 31.062,
            "VERT_INFO/PANESWIDE": 2,
            "HORIZ_INFO/HORIZONTALLENGTH": 24.85,
            "HORIZ_INFO/PANESTALL": 2,
            "VERT_DADO_INFO/V_LI": 15.527,
            "VERT_DADO_INFO/VIDX": 15.834,
            "VERT_DADO_INFO/VIDXCTR": "NULL",
            "HORIZ_DADO_INFO/H_LI": 12.416,
            "HORIZ_DADO_INFO/HIDX": 12.728,
            "HORIZ_DADO_INFO/HIDXCTR": "NULL",
            "PROFILEWIDTH/VERTPROFILEWIDTH": 0.875,
            "PROFILEWIDTH/HORIZPROFILEWIDTH": 0.875
        },
        "customFields": {
            "ProductLine": "ACCW",
            "Finish": "PAINTED",
            "OrderType": "AW850",
            "Pattern": "COL",
            "UnitSize": "1880",
            "ExteriorColor": "WH",
            "InteriorColor": "PR",
            "Type": "EXTR"
        }
    }
]